StarskyPack_py/_init_.py
StarskyPack_py/module.py
starskypack_py-0.0.1.dist-info/licenses/LICENCE
starskypack_py-0.0.1.dist-info/METADATA
starskypack_py-0.0.1.dist-info/WHEEL
starskypack_py-0.0.1.dist-info/top_level.txt
starskypack_py-0.0.1.dist-info/RECORD
