Metadata-Version: 2.4
Name: StarskyPack_py
Version: 0.0.1
Summary: package de vérification
Home-page: 
Author: Starsky.ESS
Author-email: iama.atomic23@gmail.com
License: MIT
Requires-Python: >=3.8
License-File: LICENCE
Dynamic: author
Dynamic: author-email
Dynamic: description-content-type
Dynamic: license
Dynamic: license-file
Dynamic: requires-python
Dynamic: summary
